Metadata-Version: 2.1
Name: mtg-proxyprint
Version: 1.1.1
Summary: Simple command line tool to create MTG deck proxies
Home-page: https://gitlab.com/snapcaster/proxyprinter
Author: Michael Sobczak
Author-email: michaelsobczak54@gmail.com
License: Creative Commons Attribution-Noncommercial-Share Alike license
Platform: UNKNOWN
